{
  "instrument": "Violin",
  "eras": [
    {
      "name": "Baroque",
      "startYear": 1600,
      "endYear": 1750,
      "color": "#E3F2FD"
    },
    {
      "name": "Classical",
      "startYear": 1730,
      "endYear": 1820,
      "color": "#FFF3E0"
    },
    {
      "name": "Romantic",
      "startYear": 1800,
      "endYear": 1910,
      "color": "#FCE4EC"
    },
    {
      "name": "Modern",
      "startYear": 1890,
      "endYear": 1975,
      "color": "#E8F5E9"
    },
    {
      "name": "Contemporary",
      "startYear": 1950,
      "endYear": 2030,
      "color": "#F3E5F5"
    }
  ],
  "peopleIds": [
    "bach",
    "handel",
    "vivaldi",
    "corelli",
    "tartini",
    "geminiani",
    "locatelli",
    "leclair",
    "viotti",
    "rode",
    "kreutzer",
    "baillot",
    "spohr",
    "beethoven",
    "schubert",
    "mendelssohn",
    "brahms",
    "tchaikovsky",
    "dvorak",
    "grieg",
    "faure",
    "paganini",
    "vieuxtemps",
    "wieniawski",
    "sarasate",
    "joachim",
    "auer",
    "ysaye",
    "kreisler",
    "debussy",
    "ravel",
    "bartok",
    "stravinsky",
    "prokofiev",
    "shostakovich",
    "britten",
    "barber",
    "glass",
    "part",
    "adams",
    "ades",
    "heifetz",
    "oistrakh",
    "menuhin",
    "milstein",
    "stern",
    "szeryng",
    "grumiaux",
    "kogan",
    "haendel",
    "perlman",
    "zukerman",
    "kremer",
    "mutter",
    "vengerov",
    "hahn",
    "jansen",
    "bell",
    "shaham",
    "chen"
  ]
}
